{
    "backend": "django",
    "db_name": "",
    "db_pass": "",
    "db_type": "mysql",
    "db_user": "",
    "dbms": "1",
    "description": "generated product",
    "design": "datta-able",
    "docker": "0",
    "err_code": 0,
    "frontend": "",
    "heroku": "0",
    "pattern": "mvc",
    "pro": "0",
    "task_id": "e5be3e09-5226-4e00-8db1-0c9cff1773dc",
    "task_info": "Upload Sources [0%] - 163 files",
    "task_output": "e5be3e09-5226-4e00-8db1-0c9cff1773dc.zip",
    "task_result": "SUCCESS",
    "task_state": "RUNNING",
    "task_ts_end": "2023-02-06-09-49-28",
    "task_ts_start": "2023-02-06-09-49-26"
}